{
  "app": {
    "[project]/handmade-arts-e-commerce/app/_not-found/page": [
      "static/media/caa3a2e1cccd8315-s.p.853070df.woff2",
      "static/media/797e433ab948586e-s.p.dbea232f.woff2"
    ],
    "[project]/handmade-arts-e-commerce/app/admin/(protected)/categories/page": [
      "static/media/caa3a2e1cccd8315-s.p.853070df.woff2",
      "static/media/797e433ab948586e-s.p.dbea232f.woff2"
    ],
    "[project]/handmade-arts-e-commerce/app/admin/(protected)/dashboard/page": [
      "static/media/caa3a2e1cccd8315-s.p.853070df.woff2",
      "static/media/797e433ab948586e-s.p.dbea232f.woff2"
    ],
    "[project]/handmade-arts-e-commerce/app/admin/(protected)/orders/page": [
      "static/media/caa3a2e1cccd8315-s.p.853070df.woff2",
      "static/media/797e433ab948586e-s.p.dbea232f.woff2"
    ],
    "[project]/handmade-arts-e-commerce/app/admin/(protected)/products/page": [
      "static/media/caa3a2e1cccd8315-s.p.853070df.woff2",
      "static/media/797e433ab948586e-s.p.dbea232f.woff2"
    ],
    "[project]/handmade-arts-e-commerce/app/admin/(protected)/promotions/new/page": [
      "static/media/caa3a2e1cccd8315-s.p.853070df.woff2",
      "static/media/797e433ab948586e-s.p.dbea232f.woff2"
    ],
    "[project]/handmade-arts-e-commerce/app/admin/(protected)/users/page": [
      "static/media/caa3a2e1cccd8315-s.p.853070df.woff2",
      "static/media/797e433ab948586e-s.p.dbea232f.woff2"
    ],
    "[project]/handmade-arts-e-commerce/app/admin/login/page": [
      "static/media/caa3a2e1cccd8315-s.p.853070df.woff2",
      "static/media/797e433ab948586e-s.p.dbea232f.woff2"
    ],
    "[project]/handmade-arts-e-commerce/app/checkout/page": [
      "static/media/caa3a2e1cccd8315-s.p.853070df.woff2",
      "static/media/797e433ab948586e-s.p.dbea232f.woff2"
    ],
    "[project]/handmade-arts-e-commerce/app/choose-seller/page": [
      "static/media/caa3a2e1cccd8315-s.p.853070df.woff2",
      "static/media/797e433ab948586e-s.p.dbea232f.woff2"
    ],
    "[project]/handmade-arts-e-commerce/app/dashboard/page": [
      "static/media/caa3a2e1cccd8315-s.p.853070df.woff2",
      "static/media/797e433ab948586e-s.p.dbea232f.woff2"
    ],
    "[project]/handmade-arts-e-commerce/app/login/page": [
      "static/media/caa3a2e1cccd8315-s.p.853070df.woff2",
      "static/media/797e433ab948586e-s.p.dbea232f.woff2"
    ],
    "[project]/handmade-arts-e-commerce/app/orders/page": [
      "static/media/caa3a2e1cccd8315-s.p.853070df.woff2",
      "static/media/797e433ab948586e-s.p.dbea232f.woff2"
    ],
    "[project]/handmade-arts-e-commerce/app/page": [
      "static/media/caa3a2e1cccd8315-s.p.853070df.woff2",
      "static/media/797e433ab948586e-s.p.dbea232f.woff2"
    ],
    "[project]/handmade-arts-e-commerce/app/payment/page": [
      "static/media/caa3a2e1cccd8315-s.p.853070df.woff2",
      "static/media/797e433ab948586e-s.p.dbea232f.woff2"
    ],
    "[project]/handmade-arts-e-commerce/app/private/page": [
      "static/media/caa3a2e1cccd8315-s.p.853070df.woff2",
      "static/media/797e433ab948586e-s.p.dbea232f.woff2"
    ],
    "[project]/handmade-arts-e-commerce/app/products/[id]/page": [
      "static/media/caa3a2e1cccd8315-s.p.853070df.woff2",
      "static/media/797e433ab948586e-s.p.dbea232f.woff2"
    ],
    "[project]/handmade-arts-e-commerce/app/seller/categories/page": [
      "static/media/caa3a2e1cccd8315-s.p.853070df.woff2",
      "static/media/797e433ab948586e-s.p.dbea232f.woff2"
    ],
    "[project]/handmade-arts-e-commerce/app/seller/dashboard/page": [
      "static/media/caa3a2e1cccd8315-s.p.853070df.woff2",
      "static/media/797e433ab948586e-s.p.dbea232f.woff2"
    ],
    "[project]/handmade-arts-e-commerce/app/seller/login/page": [
      "static/media/caa3a2e1cccd8315-s.p.853070df.woff2",
      "static/media/797e433ab948586e-s.p.dbea232f.woff2"
    ],
    "[project]/handmade-arts-e-commerce/app/seller/orders/page": [
      "static/media/caa3a2e1cccd8315-s.p.853070df.woff2",
      "static/media/797e433ab948586e-s.p.dbea232f.woff2"
    ],
    "[project]/handmade-arts-e-commerce/app/seller/products/new/page": [
      "static/media/caa3a2e1cccd8315-s.p.853070df.woff2",
      "static/media/797e433ab948586e-s.p.dbea232f.woff2"
    ],
    "[project]/handmade-arts-e-commerce/app/seller/products/page": [
      "static/media/caa3a2e1cccd8315-s.p.853070df.woff2",
      "static/media/797e433ab948586e-s.p.dbea232f.woff2"
    ],
    "[project]/handmade-arts-e-commerce/app/seller/register/page": [
      "static/media/caa3a2e1cccd8315-s.p.853070df.woff2",
      "static/media/797e433ab948586e-s.p.dbea232f.woff2"
    ],
    "[project]/handmade-arts-e-commerce/app/seller/settings/page": [
      "static/media/caa3a2e1cccd8315-s.p.853070df.woff2",
      "static/media/797e433ab948586e-s.p.dbea232f.woff2"
    ],
    "[project]/handmade-arts-e-commerce/app/seller/users/page": [
      "static/media/caa3a2e1cccd8315-s.p.853070df.woff2",
      "static/media/797e433ab948586e-s.p.dbea232f.woff2"
    ],
    "[project]/handmade-arts-e-commerce/app/signup/page": [
      "static/media/caa3a2e1cccd8315-s.p.853070df.woff2",
      "static/media/797e433ab948586e-s.p.dbea232f.woff2"
    ],
    "[project]/handmade-arts-e-commerce/app/wishlist/page": [
      "static/media/caa3a2e1cccd8315-s.p.853070df.woff2",
      "static/media/797e433ab948586e-s.p.dbea232f.woff2"
    ]
  },
  "appUsingSizeAdjust": true,
  "pages": {},
  "pagesUsingSizeAdjust": false
}